pioreactor_calibration_shrinkage/LEADER_ONLY
pioreactor_calibration_shrinkage/__init__.py
pioreactor_calibration_shrinkage-1.0.0.dist-info/METADATA
pioreactor_calibration_shrinkage-1.0.0.dist-info/WHEEL
pioreactor_calibration_shrinkage-1.0.0.dist-info/entry_points.txt
pioreactor_calibration_shrinkage-1.0.0.dist-info/top_level.txt
pioreactor_calibration_shrinkage-1.0.0.dist-info/RECORD
