Metadata-Version: 2.2
Name: pioreactor-calibration-shrinkage
Version: 1.0.0
Summary: Fuse multiple calibrations into better calibrations
Home-page: https://github.com/Pioreactor/pioreactor-calibration-shrinkage
Author: Pioreactor
Author-email: hello@pioreactor.com
License: MIT
Dynamic: author
Dynamic: author-email
Dynamic: description
Dynamic: description-content-type
Dynamic: home-page
Dynamic: license
Dynamic: summary
